morningstar_descriptors/__init__.py
morningstar_descriptors/_morningstar_descriptors.py
morningstar_descriptors-0.1.0.dist-info/DESCRIPTION.rst
morningstar_descriptors-0.1.0.dist-info/METADATA
morningstar_descriptors-0.1.0.dist-info/RECORD
morningstar_descriptors-0.1.0.dist-info/WHEEL
morningstar_descriptors-0.1.0.dist-info/metadata.json
morningstar_descriptors-0.1.0.dist-info/top_level.txt
