Metadata-Version: 2.0
Name: morningstar-descriptors
Version: 0.1.0
Summary: get financial descriptors from morningstar
Home-page: http://github.com/gykovacs/morningstar_descriptors
Author: Gyorgy Kovacs
Author-email: gyuriofkovacs@gmail.com
License: GPL3
Keywords: morningstar descriptor financial-statement
Platform: UNKNOWN
Classifier: Development Status :: 3 - Alpha
Classifier: License :: OSI Approved :: GNU General Public License v3 (GPLv3)
Classifier: Programming Language :: Python
Classifier: Topic :: Scientific/Engineering
Requires-Python: >=27, <4
Requires-Dist: requests
Requires-Dist: wikitables
Requires-Dist: pandas
